civic_utils/__init__.py
civic_utils/apps.py
civic_utils/conf.py
civic_utils/serializers.py
civic_utils/management/__init__.py
civic_utils/management/helpers.py
civic_utils/management/commands/__init__.py
civic_utils/management/commands/exportdata.py
civic_utils/management/commands/importdata.py
civic_utils/models/__init__.py
civic_utils/models/base.py
civic_utils/models/helpers.py
civic_utils/models/managers.py
civic_utils/models/mixins.py
civic_utils/models/querysets.py
civic_utils/utils/__init__.py
civic_utils/utils/aws.py
civic_utils/utils/importers.py
civic_utils/utils/rest_formats.py
politico_civic_utils-0.0.8.dist-info/LICENSE
politico_civic_utils-0.0.8.dist-info/METADATA
politico_civic_utils-0.0.8.dist-info/WHEEL
politico_civic_utils-0.0.8.dist-info/top_level.txt
politico_civic_utils-0.0.8.dist-info/RECORD
