Metadata-Version: 2.1
Name: politico-civic-utils
Version: 0.0.8
Summary: Shared utilities for POLITICO Civic apps
Home-page: https://github.com/The-Politico/politico-civic-utils/
Author: POLITICO interactive news
Author-email: interactives@politico.com
License: MIT
Download-URL: https://github.com/The-Politico/politico-civic-utils/archive/0.0.8.tar.gz
Platform: UNKNOWN
Classifier: Development Status :: 3 - Alpha
Classifier: Framework :: Django
Classifier: Framework :: Django :: 2.0
Classifier: Intended Audience :: Developers
Classifier: Intended Audience :: Information Technology
Classifier: License :: OSI Approved :: MIT License
Classifier: Operating System :: OS Independent
Classifier: Programming Language :: Python :: 3
Classifier: Programming Language :: Python :: 3.5
Classifier: Programming Language :: Python :: 3.6
Classifier: Topic :: Internet :: WWW/HTTP
Requires-Dist: django
Requires-Dist: django-uuslug
Requires-Dist: djangorestframework
Requires-Dist: boto3
Requires-Dist: crayons
Requires-Dist: psycopg2-binary
Requires-Dist: progress
Provides-Extra: test
Requires-Dist: pytest ; extra == 'test'
